nocd/__init__.py
nocd/main.py
nocd-1.1.0.dist-info/METADATA
nocd-1.1.0.dist-info/WHEEL
nocd-1.1.0.dist-info/entry_points.txt
nocd-1.1.0.dist-info/top_level.txt
nocd-1.1.0.dist-info/RECORD
