Metadata-Version: 2.4
Name: nocd
Version: 1.1.0
Summary: Run commands in another directory without cd
Author-email: "@readwithai" <talwrii@example.com>
License: MIT
Project-URL: Homepage, https://github.com/talwrii/nocd
Project-URL: Bug Reports, https://github.com/talwrii/nocd/issues
Project-URL: Source, https://github.com/talwrii/nocd
Keywords: cli,directory,command,productivity,tools
Classifier: Development Status :: 4 - Beta
Classifier: Environment :: Console
Classifier: Intended Audience :: Developers
Classifier: Intended Audience :: System Administrators
Classifier: License :: OSI Approved :: MIT License
Classifier: Operating System :: OS Independent
Classifier: Programming Language :: Python :: 3
Classifier: Programming Language :: Python :: 3.8
Classifier: Programming Language :: Python :: 3.9
Classifier: Programming Language :: Python :: 3.10
Classifier: Programming Language :: Python :: 3.11
Classifier: Programming Language :: Python :: 3.12
Classifier: Topic :: System :: Shells
Classifier: Topic :: Utilities
Classifier: Topic :: Software Development :: Libraries :: Python Modules
Requires-Python: >=3.8
Provides-Extra: dev
Requires-Dist: pytest>=6.0; extra == "dev"
Requires-Dist: black; extra == "dev"
Requires-Dist: flake8; extra == "dev"
Requires-Dist: mypy; extra == "dev"
